CHANGES.txt
MANIFEST.in
README.txt
bootstrap.py
setup.py
fanstatictemplate/__init__.py
fanstatictemplate/test_template.py
fanstatictemplate.egg-info/PKG-INFO
fanstatictemplate.egg-info/SOURCES.txt
fanstatictemplate.egg-info/dependency_links.txt
fanstatictemplate.egg-info/entry_points.txt
fanstatictemplate.egg-info/not-zip-safe
fanstatictemplate.egg-info/requires.txt
fanstatictemplate.egg-info/top_level.txt
fanstatictemplate/template_code/__init__.py_tmpl
fanstatictemplate/template_code/test_+library_name_lower+.txt_tmpl
fanstatictemplate/template_code/resources/README.txt
fanstatictemplate/template_metadata/+dot+hgignore
fanstatictemplate/template_metadata/CHANGES.txt_tmpl
fanstatictemplate/template_metadata/LICENSE.txt
fanstatictemplate/template_metadata/MANIFEST.in_tmpl
fanstatictemplate/template_metadata/README.txt_tmpl
fanstatictemplate/template_metadata/bootstrap.py
fanstatictemplate/template_metadata/buildout.cfg_tmpl
fanstatictemplate/template_metadata/setup.py_tmpl