Metadata-Version: 1.0
Name: fanstatictemplate
Version: 1.3
Summary: Fanstatic package template
Home-page: http://fanstatic.org
Author: Fanstatic Developers
Author-email: fanstatic@googlegroups.com
License: BSD
Platform: UNKNOWN
